repindex/__init__.py
repindex/repindex.py
repindex-0.3.3.dist-info/licenses/LICENSE
repindex-0.3.3.dist-info/METADATA
repindex-0.3.3.dist-info/WHEEL
repindex-0.3.3.dist-info/entry_points.txt
repindex-0.3.3.dist-info/top_level.txt
repindex-0.3.3.dist-info/RECORD
