Metadata-Version: 2.4
Name: repindex
Version: 0.3.3
Summary: A tool to index a repository and generate structured outputs for visualization and documentation.
Author-email: Simon Yang <simon@example.com>
License: MIT
Project-URL: Homepage, https://github.com/yangsi7/repindex
Project-URL: Bug Tracker, https://github.com/yangsi7/repindex/issues
Keywords: repository,index,documentation,dependency graph,context,llm
Classifier: Programming Language :: Python :: 3
Classifier: Operating System :: OS Independent
Requires-Python: >=3.6
License-File: LICENSE
Requires-Dist: setuptools>=61.0
Provides-Extra: clipboard
Requires-Dist: pyperclip>=1.8.0; extra == "clipboard"
Provides-Extra: dev
Requires-Dist: flake8>=5.0.0; extra == "dev"
Requires-Dist: pytest>=7.0.0; extra == "dev"
Dynamic: license-file
